pigai/__init__.py
pigai/core.py
pigai/exceptions.py
pigai/utils.py
pigai_gpt2-0.0.3.dist-info/LICENSE
pigai_gpt2-0.0.3.dist-info/METADATA
pigai_gpt2-0.0.3.dist-info/WHEEL
pigai_gpt2-0.0.3.dist-info/top_level.txt
pigai_gpt2-0.0.3.dist-info/RECORD
