Metadata-Version: 2.1
Name: pigai-gpt2
Version: 0.0.3
Summary: 批改网写作助手，根据配置自动生成并提交英语作文。
Home-page: https://github.com/QIN2DIM/PigAI_GPT2
Author: QIN2DIM
Author-email: qinse.top@foxmail.com
License: GNU General Public License v3.0
Keywords: pigai,gpt2
Platform: UNKNOWN
Classifier: Topic :: Scientific/Engineering
Classifier: Topic :: Scientific/Engineering :: Artificial Intelligence
Classifier: Topic :: Software Development
Classifier: Topic :: Software Development :: Libraries
Classifier: Topic :: Software Development :: Libraries :: Python Modules
Classifier: License :: OSI Approved :: Apache Software License
Classifier: Programming Language :: Python :: 3
Requires-Python: >=3.7
License-File: LICENSE
Requires-Dist: pyyaml (~=6.0)
Requires-Dist: selenium (~=4.1.0)
Requires-Dist: loguru (~=0.6.0)
Requires-Dist: requests (~=2.27.1)
Requires-Dist: webdriver-manager (>=3.5.2)
